Workbook

Sheet Hoja1
A1: CUI | B1: SNIP | C1: Último Estado | D1: Cant. Obs. Adm. | E1: Cant. Obs. Cal. | F1: Cant. Eval. Inv. | G1: Etapa | H1: Fecha Inicio | I1: Fecha Fin | J1: Diferencial Días | K1: Monto Inversión | L1: MONITOREO | M1: MONTO CONTRATADO OBRA | N1: MONTO CONTRATADO SUPERVISION | O1: MONTO LIQUIDACIÓN OBRA | P1: MONTO LIQUIDACIÓN SUPERVISIÓN | Q1: MONTO LIQUIDACIÓN COMPLEMENTARIO
A2: 2031691 | B2: 34548 | C2: Abandono | D2: 2 | E2: 1 | F2: 0 | G2: Calidad | H2: 44431.887 | I2: 44456.503 | J2: 25 | K2: 46971858 | L2: =+VLOOKUP(A2,Hoja2!$A$2:$X$2596,19,FALSE) -> En Ejecución | M2: =+VLOOKUP(A2,Hoja2!$A$2:$X$2596,15,FALSE) -> 37327357 | N2: =+VLOOKUP(A2,Hoja2!$A$2:$X$2596,17,FALSE) -> 1420721.6 | O2: =+VLOOKUP(A2,Hoja2!$A$2:$X$2596,22,FALSE) | P2: =+VLOOKUP(A2,Hoja2!$A$2:$X$2596,23,FALSE) | Q2: =+VLOOKUP(A2,Hoja2!$A$2:$X$2596,24,FALSE)
A3: 2031691 | B3: 34548 | C3: Desestimado | D3: 1 | E3: 4 | F3: 0 | G3: Calidad | H3: 44574.722 | I3: 44768.741 | J3: 194 | K3: 46971858 | L3: =+VLOOKUP(A3,Hoja2!$A$2:$X$2596,19,FALSE) -> En Ejecución | M3: =+VLOOKUP(A3,Hoja2!$A$2:$X$2596,15,FALSE) -> 37327357 | N3: =+VLOOKUP(A3,Hoja2!$A$2:$X$2596,17,FALSE) -> 1420721.6 | O3: =+VLOOKUP(A3,Hoja2!$A$2:$X$2596,22,FALSE) | P3: =+VLOOKUP(A3,Hoja2!$A$2:$X$2596,23,FALSE) | Q3: =+VLOOKUP(A3,Hoja2!$A$2:$X$2596,24,FALSE)
A4: 2031691 | B4: 34548 | C4: Aprobado | D4: 1 | E4: 8 | F4: 0 | G4: Calidad | H4: 44993.446 | I4: 45034.775 | J4: 41 | K4: 46971858 | L4: =+VLOOKUP(A4,Hoja2!$A$2:$X$2596,19,FALSE) -> En Ejecución | M4: =+VLOOKUP(A4,Hoja2!$A$2:$X$2596,15,FALSE) -> 37327357 | N4: =+VLOOKUP(A4,Hoja2!$A$2:$X$2596,17,FALSE) -> 1420721.6 | O4: =+VLOOKUP(A4,Hoja2!$A$2:$X$2596,22,FALSE) | P4: =+VLOOKUP(A4,Hoja2!$A$2:$X$2596,23,FALSE) | Q4: =+VLOOKUP(A4,Hoja2!$A$2:$X$2596,24,FALSE)
A5: 2071970 | B5: 78623 | C5: Aprobado | D5: 2 | E5: 3 | F5: 0 | G5: Calidad | H5: 44412.822 | I5: 44434.548 | J5: 22 | K5: 9296404 | L5: =+VLOOKUP(A5,Hoja2!$A$2:$X$2596,19,FALSE) -> En Ejecución | M5: =+VLOOKUP(A5,Hoja2!$A$2:$X$2596,15,FALSE) -> 29497031 | N5: =+VLOOKUP(A5,Hoja2!$A$2:$X$2596,17,FALSE) -> 1233859.6 | O5: =+VLOOKUP(A5,Hoja2!$A$2:$X$2596,22,FALSE) | P5: =+VLOOKUP(A5,Hoja2!$A$2:$X$2596,23,FALSE) | Q5: =+VLOOKUP(A5,Hoja2!$A$2:$X$2596,24,FALSE)
A6: 2082525 | B6: 80758 | C6: Abandono | D6: 2 | E6: 0 | F6: 0 | G6: Admisibilidad | H6: 44525.445 | I6: 44539.692 | J6: 14 | K6: 67763285 | L6: =+VLOOKUP(A6,Hoja2!$A$2:$X$2596,19,FALSE) -> #N/A | M6: =+VLOOKUP(A6,Hoja2!$A$2:$X$2596,15,FALSE) -> #N/A | N6: =+VLOOKUP(A6,Hoja2!$A$2:$X$2596,17,FALSE) -> #N/A | O6: =+VLOOKUP(A6,Hoja2!$A$2:$X$2596,22,FALSE) -> #N/A | P6: =+VLOOKUP(A6,Hoja2!$A$2:$X$2596,23,FALSE) -> #N/A | Q6: =+VLOOKUP(A6,Hoja2!$A$2:$X$2596,24,FALSE) -> #N/A
A7: 2082525 | B7: 80758 | C7: Desestimado | D7: 1 | E7: 2 | F7: 0 | G7: Calidad | H7: 44606.375 | I7: 44754.615 | J7: 148 | K7: 67763285 | L7: =+VLOOKUP(A7,Hoja2!$A$2:$X$2596,19,FALSE) -> #N/A | M7: =+VLOOKUP(A7,Hoja2!$A$2:$X$2596,15,FALSE) -> #N/A | N7: =+VLOOKUP(A7,Hoja2!$A$2:$X$2596,17,FALSE) -> #N/A | O7: =+VLOOKUP(A7,Hoja2!$A$2:$X$2596,22,FALSE) -> #N/A | P7: =+VLOOKUP(A7,Hoja2!$A$2:$X$2596,23,FALSE) -> #N/A | Q7: =+VLOOKUP(A7,Hoja2!$A$2:$X$2596,24,FALSE) -> #N/A
A8: 2082525 | B8: 80758 | C8: Desestimado | D8: 1 | E8: 4 | F8: 0 | G8: Calidad | H8: 44845.729 | I8: 45096.723 | J8: 251 | K8: 67763285 | L8: =+VLOOKUP(A8,Hoja2!$A$2:$X$2596,19,FALSE) -> #N/A | M8: =+VLOOKUP(A8,Hoja2!$A$2:$X$2596,15,FALSE) -> #N/A | N8: =+VLOOKUP(A8,Hoja2!$A$2:$X$2596,17,FALSE) -> #N/A | O8: =+VLOOKUP(A8,Hoja2!$A$2:$X$2596,22,FALSE) -> #N/A | P8: =+VLOOKUP(A8,Hoja2!$A$2:$X$2596,23,FALSE) -> #N/A | Q8: =+VLOOKUP(A8,Hoja2!$A$2:$X$2596,24,FALSE) -> #N/A
A9: 2082525 | B9: 80758 | C9: Desestimado | D9: 1 | E9: 1 | F9: 0 | G9: Calidad | H9: 45322.333 | I9: 45411.746 | J9: 89 | K9: 67763285 | L9: =+VLOOKUP(A9,Hoja2!$A$2:$X$2596,19,FALSE) -> #N/A | M9: =+VLOOKUP(A9,Hoja2!$A$2:$X$2596,15,FALSE) -> #N/A | N9: =+VLOOKUP(A9,Hoja2!$A$2:$X$2596,17,FALSE) -> #N/A | O9: =+VLOOKUP(A9,Hoja2!$A$2:$X$2596,22,FALSE) -> #N/A | P9: =+VLOOKUP(A9,Hoja2!$A$2:$X$2596,23,FALSE) -> #N/A | Q9: =+VLOOKUP(A9,Hoja2!$A$2:$X$2596,24,FALSE) -> #N/A
A10: 2082525 | B10: 80758 | C10: Desestimado | D10: 5 | E10: 0 | F10: 0 | G10: Admisibilidad | H10: 45645.713 | I10: 45768.716 | J10: 123 | K10: 67763285 | L10: =+VLOOKUP(A10,Hoja2!$A$2:$X$2596,19,FALSE) -> #N/A | M10: =+VLOOKUP(A10,Hoja2!$A$2:$X$2596,15,FALSE) -> #N/A | N10: =+VLOOKUP(A10,Hoja2!$A$2:$X$2596,17,FALSE) -> #N/A | O10: =+VLOOKUP(A10,Hoja2!$A$2:$X$2596,22,FALSE) -> #N/A | P10: =+VLOOKUP(A10,Hoja2!$A$2:$X$2596,23,FALSE) -> #N/A | Q10: =+VLOOKUP(A10,Hoja2!$A$2:$X$2596,24,FALSE) -> #N/A
A11: 2073692 | B11: 83462 | C11: Desestimado | D11: 2 | E11: 1 | F11: 0 | G11: Calidad | H11: 44214.508 | I11: 44350.084 | J11: 136 | K11: 16380511 | L11: =+VLOOKUP(A11,Hoja2!$A$2:$X$2596,19,FALSE) -> En Ejecución | M11: =+VLOOKUP(A11,Hoja2!$A$2:$X$2596,15,FALSE) -> 21560455 | N11: =+VLOOKUP(A11,Hoja2!$A$2:$X$2596,17,FALSE) -> 1056645.9 | O11: =+VLOOKUP(A11,Hoja2!$A$2:$X$2596,22,FALSE) | P11: =+VLOOKUP(A11,Hoja2!$A$2:$X$2596,23,FALSE) | Q11: =+VLOOKUP(A11,Hoja2!$A$2:$X$2596,24,FALSE)
A12: 2073692 | B12: 83462 | C12: Desestimado | D12: 3 | E12: 3 | F12: 0 | G12: Calidad | H12: 44456.805 | I12: 44607.367 | J12: 151 | K12: 16380511 | L12: =+VLOOKUP(A12,Hoja2!$A$2:$X$2596,19,FALSE) -> En Ejecución | M12: =+VLOOKUP(A12,Hoja2!$A$2:$X$2596,15,FALSE) -> 21560455 | N12: =+VLOOKUP(A12,Hoja2!$A$2:$X$2596,17,FALSE) -> 1056645.9 | O12: =+VLOOKUP(A12,Hoja2!$A$2:$X$2596,22,FALSE) | P12: =+VLOOKUP(A12,Hoja2!$A$2:$X$2596,23,FALSE) | Q12: =+VLOOKUP(A12,Hoja2!$A$2:$X$2596,24,FALSE)
A13: 2073692 | B13: 83462 | C13: Aprobado | D13: 4 | E13: 4 | F13: 0 | G13: Calidad | H13: 44629.882 | I13: 44715.559 | J13: 86 | K13: 16380511 | L13: =+VLOOKUP(A13,Hoja2!$A$2:$X$2596,19,FALSE) -> En Ejecución | M13: =+VLOOKUP(A13,Hoja2!$A$2:$X$2596,15,FALSE) -> 21560455 | N13: =+VLOOKUP(A13,Hoja2!$A$2:$X$2596,17,FALSE) -> 1056645.9 | O13: =+VLOOKUP(A13,Hoja2!$A$2:$X$2596,22,FALSE) | P13: =+VLOOKUP(A13,Hoja2!$A$2:$X$2596,23,FALSE) | Q13: =+VLOOKUP(A13,Hoja2!$A$2:$X$2596,24,FALSE)
... A776: 2703585 | B776: 2703585 | C776: Observada | D776: 2 | E776: 0 | F776: 0 | G776: Admisibilidad | H776: 45936.464 | I776: 45950.451 | J776: 14 | K776: 1.2418542e+08 | L776: =+VLOOKUP(A776,Hoja2!$A$2:$X$2596,19,FALSE) -> #N/A | M776: =+VLOOKUP(A776,Hoja2!$A$2:$X$2596,15,FALSE) -> #N/A | N776: =+VLOOKUP(A776,Hoja2!$A$2:$X$2596,17,FALSE) -> #N/A | O776: =+VLOOKUP(A776,Hoja2!$A$2:$X$2596,22,FALSE) -> #N/A | P776: =+VLOOKUP(A776,Hoja2!$A$2:$X$2596,23,FALSE) -> #N/A | Q776: =+VLOOKUP(A776,Hoja2!$A$2:$X$2596,24,FALSE) -> #N/A

Sheet Hoja2
A1: 1 | B1: 2 | C1: 3 | D1: 4 | E1: 5 | F1: 6 | G1: 7 | H1: 8 | I1: 9 | J1: 10 | K1: 11 | L1: 12 | M1: 13 | N1: 14 | O1: 15 | P1: 16 | Q1: 17 | R1: 18 | S1: 19 | T1: 20 | U1: 21 | V1: 22 | W1: 23 | X1: 24
A2: CODIGO_UNIFICADO | B2: monto_snip | C2: id_proyecto | D2: subsector | E2: subprograma | F2: cod_snip | G2: monto_inversion | H2: CostoActual | I2: DevengadoAcumulado | J2: DevengadoTotal2019 | K2: PimTotal2019 | L2: estadoPIP | M2: Tipo | N2: MontoReferencial | O2: MontoContratado | P2: MontoReferencial2 | Q2: MontoContratado2 | R2: EstadoEjecucion | S2: Estado | T2: SubEstado | U2: SubEstado2 | V2: montoLiquidacion | W2: montoLiqSupervision | X2: montoLiqObraComplementaria
A3: 2015097 | B3: 80000 | C3: 31084 | D3: PNSU | E3: UNIDAD DE GESTION TERRITORIAL - UGT | F3: 33800 | G3: 80000 | H3: 80000 | I3: 0 | J3: 0 | K3: 0 | L3: DESACTIVADO PERMANENTE | M3: OBRA | R3: Concluido - En Liquidación | S3: Concluido | T3: En Liquidación | V3: 69467.85 | W3: 0 | X3: 0
A4: 2015662 | B4: 8456770 | C4: 31098 | D4: PNSU | E4: UNIDAD DE GESTION TERRITORIAL - UGT | F4: 5206 | G4: 8456770 | H4: 8456770 | I4: 570492.9 | J4: 0 | K4: 0 | L4: ACTIVO | M4: OBRA | R4: Concluido - Convenio Cerrado | S4: Concluido | T4: Convenio Cerrado | V4: 2707542.2 | W4: 0 | X4: 0
A5: 2017383 | B5: 20279145 | C5: 46823 | D5: PNSU | E5: UNIDAD DE GESTION TERRITORIAL - UGT | F5: 3101 | G5: 62312762 | H5: 1.1932883e+08 | I5: 87313828 | J5: 0 | K5: 66000 | L5: ACTIVO | M5: OBRA (SALDO) | N5: 49940958 | O5: 49940958 | P5: 731106 | Q5: 320201 | R5: Convenio y/o Contrato Resuelto | S5: Convenio y/o Contrato Resuelto
A6: 2017384 | B6: 141137863 | C6: 42121 | D6: PNSU | E6: UNIDAD DE PROYECTOS - AREA DE ESTUDIOS | F6: 3089 | G6: 141137863 | H6: 141137863 | I6: 639937.47 | J6: 0 | K6: 0 | L6: ACTIVO | M6: EXPEDIENTE TECNICO | R6: En elaboración - En Proceso | S6: En elaboración | T6: En Proceso
A7: 2018438 | B7: 1595256 | C7: 30947 | D7: PNSU | E7: UNIDAD DE GESTION TERRITORIAL - UGT | F7: 8727 | G7: 1595256 | H7: 1595256 | I7: 457956.79 | J7: 0 | K7: 0 | L7: CERRADO | M7: OBRA | N7: 1583190.6 | O7: 1330412.3 | R7: Concluido - En Liquidación | S7: Concluido | T7: En Liquidación | V7: 0 | W7: 0 | X7: 0
A8: 2018570 | B8: 1279390 | C8: 31284 | D8: PNSU | E8: UNIDAD DE GESTION TERRITORIAL - UGT | F8: 7331 | G8: 1279390 | H8: 1279390 | I8: 2320452.9 | J8: 0 | K8: 0 | L8: ACTIVO | M8: OBRA | R8: Concluido - Convenio Cerrado | S8: Concluido | T8: Convenio Cerrado | V8: 2004564.6 | W8: 0 | X8: 0
A9: 2022649 | B9: 26201116 | C9: 30952 | D9: PNSU | E9: UNIDAD DE GESTION TERRITORIAL - UGT | F9: 12762 | G9: 25234035 | H9: 25234035 | I9: 26804759 | J9: 0 | K9: 0 | L9: CERRADO | M9: OBRA | N9: 25294133 | O9: 25234035 | P9: 2022666.8 | Q9: 1869692 | R9: Concluido - En Liquidación | S9: Concluido | T9: En Liquidación | V9: 24818942 | W9: 0 | X9: 0
A10: 2023386 | B10: 371015 | C10: 30072 | D10: PNSU | E10: UNIDAD DE GESTION TERRITORIAL - UGT | F10: 22433 | G10: 371015 | H10: 371015 | I10: 9999.5 | J10: 0 | K10: 0 | L10: CERRADO | M10: OBRA | N10: 0 | O10: 4799112 | R10: Concluido - Convenio Cerrado | S10: Concluido | T10: Convenio Cerrado | V10: 0 | W10: 0 | X10: 0
A11: 2024436 | B11: 11213593 | C11: 30762 | D11: PNSU | E11: UNIDAD DE GESTION TERRITORIAL - UGT | F11: 19791 | G11: 13479302 | H11: 13479302 | I11: 16031168 | J11: 0 | K11: 0 | L11: ACTIVO | M11: OBRA | N11: 11213590 | O11: 10948312 | P11: 310000 | Q11: 300700 | R11: Concluido - Convenio Cerrado | S11: Concluido | T11: Convenio Cerrado | V11: 13642900 | W11: 483672.6 | X11: 0
A12: 2025625 | B12: 541396 | C12: 31053 | D12: PNSU | E12: UNIDAD DE GESTION TERRITORIAL - UGT | F12: 18175 | G12: 687791 | H12: 687791 | I12: 370898.6 | J12: 0 | K12: 0 | L12: ACTIVO | M12: OBRA | R12: Concluido - Convenio Cerrado | S12: Concluido | T12: Convenio Cerrado | V12: 329846.77 | W12: 0 | X12: 0
A13: 2025708 | B13: 10956790 | C13: 30384 | D13: PNSU | E13: UNIDAD DE GESTION TERRITORIAL - UGT | F13: 20077 | G13: 9230541.7 | H13: 6462115.3 | I13: 9230841.7 | J13: 0 | K13: 0 | L13: ACTIVO | M13: OBRA | N13: 6154397.9 | O13: 6462115.3 | P13: 173478.96 | Q13: 156131.07 | R13: Concluido - Recepción observada | S13: Concluido | T13: Recepción observada
A14: 2026794 | B14: 813093 | C14: 30496 | D14: PNSU | E14: UNIDAD DE GESTION TERRITORIAL - UGT | F14: 24381 | G14: 813093 | H14: 813093 | I14: 0 | J14: 0 | K14: 0 | L14: DESACTIVADO PERMANENTE | M14: OBRA | N14: 745887.05 | O14: 671298.35 | R14: Concluido - Convenio Cerrado | S14: Concluido | T14: Convenio Cerrado | V14: 691558.37 | W14: 0 | X14: 0
A15: 2027765 | B15: 2135621 | C15: 29856 | D15: PNSU | E15: UNIDAD DE GESTION TERRITORIAL - UGT | F15: 27692 | G15: 2135621 | H15: 2135621 | I15: 151790 | J15: 0 | K15: 0 | L15: CERRADO | M15: OBRA | N15: 1686585 | O15: 1838377.6 | P15: 68181.82 | Q15: 57000 | R15: Concluido - Convenio Cerrado | S15: Concluido | T15: Convenio Cerrado | V15: 963670.02 | W15: 58539 | X15: 0
A16: 2028330 | B16: 1016474 | C16: 31083 | D16: PNSU | E16: UNIDAD DE GESTION TERRITORIAL - UGT | F16: 15977 | G16: 1597845 | H16: 1597845 | I16: 1217914.6 | J16: 0 | K16: 0 | L16: CERRADO | M16: OBRA | R16: Concluido - Convenio Cerrado | S16: Concluido | T16: Convenio Cerrado | V16: 2137063.5 | W16: 7784.34 | X16: 0
A17: 2028948 | B17: 1409802 | C17: 31005 | D17: PNSU | E17: UNIDAD DE GESTION TERRITORIAL - UGT | F17: 7635 | G17: 1409802 | H17: 1409802 | I17: 0 | J17: 0 | K17: 0 | L17: DESACTIVADO PERMANENTE | M17: OBRA | R17: Concluido - Convenio Cerrado | S17: Concluido | T17: Convenio Cerrado | V17: 836881.67 | W17: 0 | X17: 0
A18: 2029016 | B18: 2807949 | C18: 31242 | D18: PNSU | E18: UNIDAD DE GESTION TERRITORIAL - UGT | F18: 27525 | G18: 4694693 | H18: 4694693 | I18: 5007805.8 | J18: 0 | K18: 0 | L18: CERRADO | M18: OBRA | R18: Concluido - Convenio Cerrado | S18: Concluido | T18: Convenio Cerrado | V18: 3697387.3 | W18: 0 | X18: 0
A19: 2030269 | B19: 1460854 | C19: 30147 | D19: PNSU | E19: UNIDAD DE GESTION TERRITORIAL - UGT | F19: 30412 | G19: 0 | M19: OBRA | N19: 1000428.7 | O19: 900385.87 | P19: 1000428.7 | Q19: 0 | R19: Concluido - Convenio Cerrado | S19: Concluido | T19: Convenio Cerrado | V19: 933523.55 | W19: 0 | X19: 0
A20: 2030270 | B20: 636540 | C20: 30149 | D20: PNSU | E20: UNIDAD DE GESTION TERRITORIAL - UGT | F20: 30431 | G20: 372895.39 | H20: 372895.39 | I20: 0 | J20: 0 | K20: 0 | L20: CERRADO | M20: OBRA | N20: 380081 | O20: 342073 | P20: 380081 | Q20: 0 | R20: Concluido - Convenio Cerrado | S20: Concluido | T20: Convenio Cerrado | V20: 254511.42 | W20: 0 | X20: 0
A21: 2030537 | B21: 8645797 | C21: 30638 | D21: PNSU | E21: UNIDAD DE GESTION TERRITORIAL - UGT | F21: 1872 | G21: 8645797 | H21: 8645797 | I21: 8539912.4 | J21: 0 | K21: 0 | L21: CERRADO | M21: OBRA | N21: 8645797 | O21: 9207680 | P21: 185254.44 | Q21: 155676 | R21: Concluido - Liquidada | S21: Concluido | T21: Liquidada | V21: 0 | W21: 155676 | X21: 0
A22: 2030538 | B22: 1993909 | C22: 30861 | D22: PNSU | E22: UNIDAD DE GESTION TERRITORIAL - UGT | F22: 12190 | G22: 4072124.3 | H22: 4072124.3 | I22: 4169239.9 | J22: 0 | K22: 0 | L22: CERRADO | M22: OBRA | N22: 1919020 | O22: 1919020 | P22: 60000 | Q22: 54000 | R22: Concluido - Convenio Cerrado | S22: Concluido | T22: Convenio Cerrado | V22: 3359260.9 | W22: 0 | X22: 0
A23: 2030555 | B23: 1805329 | C23: 30722 | D23: PNSU | E23: UNIDAD DE GESTION TERRITORIAL - UGT | F23: 26583 | G23: 1805329 | H23: 1805329 | I23: 0 | J23: 0 | K23: 0 | L23: DESACTIVADO PERMANENTE | M23: OBRA | N23: 1315486.8 | O23: 1183938.2 | P23: 42697 | Q23: 38427.3 | R23: Concluido - Convenio Cerrado | S23: Concluido | T23: Convenio Cerrado | V23: 1183938.2 | W23: 0 | X23: 0
A24: 2030556 | B24: 1691681 | C24: 30734 | D24: PNSU | E24: UNIDAD DE GESTION TERRITORIAL - UGT | F24: 26787 | G24: 1691681 | H24: 1691681 | I24: 1903517.8 | J24: 0 | K24: 0 | L24: CERRADO | M24: OBRA | N24: 1824351 | O24: 1824351 | P24: 36130.02 | Q24: 32517.02 | R24: Concluido - Convenio Cerrado | S24: Concluido | T24: Convenio Cerrado | V24: 1862667.6 | W24: 0 | X24: 0
A25: 2016436 | B25: 490932.29 | C25: 30685 | D25: PNSU | E25: UNIDAD DE GESTION TERRITORIAL - UGT | F25: 7672 | G25: 490932.29 | H25: 490932.29 | I25: 667964.28 | J25: 0 | K25: 0 | L25: ACTIVO | M25: OBRA | N25: 143713 | O25: 140839 | R25: Concluido - Convenio Cerrado | S25: Concluido | T25: Convenio Cerrado | V25: 148001.84 | W25: 0 | X25: 0
A26: 2017265 | B26: 1893011.8 | C26: 30694 | D26: PNSU | E26: UNIDAD DE GESTION TERRITORIAL - UGT | F26: 7008 | G26: 1893011.8 | H26: 1893011.8 | I26: 2197967.6 | J26: 0 | K26: 0 | L26: CERRADO | M26: OBRA | N26: 555904 | O26: 555904 | P26: 555904 | Q26: 13086.34 | R26: Concluido - Convenio Cerrado | S26: Concluido | T26: Convenio Cerrado | V26: 711029.89 | W26: 0 | X26: 0
A27: 2018910 | B27: 1486177 | C27: 30950 | D27: PNSU | E27: UNIDAD DE GESTION TERRITORIAL - UGT | F27: 11773 | G27: 1486177 | H27: 1486177 | I27: 2338064.4 | J27: 0 | K27: 0 | L27: CERRADO | M27: OBRA | N27: 2060703.9 | O27: 1645099.7 | R27: Concluido - En Liquidación | S27: Concluido | T27: En Liquidación | V27: 768349.68 | W27: 0 | X27: 2234300.5
A28: 2018978 | B28: 1970046 | C28: 31233 | D28: PNSU | E28: UNIDAD DE GESTION TERRITORIAL - UGT | F28: 4319 | G28: 1999586.3 | H28: 1999586.3 | I28: 2144524.7 | J28: 0 | K28: 0 | L28: CERRADO | M28: OBRA | R28: Concluido - En Liquidación | S28: Concluido | T28: En Liquidación | V28: 2136756.8 | W28: 0 | X28: 0
A29: 2019410 | B29: 843490 | C29: 29936 | D29: PNSU | E29: UNIDAD DE GESTION TERRITORIAL - UGT | F29: 17787 | G29: 843490 | H29: 843490 | I29: 0 | J29: 0 | K29: 0 | L29: DESACTIVADO PERMANENTE | M29: OBRA | N29: 888489 | O29: 888489 | P29: 888489 | Q29: 0 | R29: Concluido - Convenio Cerrado | S29: Concluido | T29: Convenio Cerrado | V29: 872881.74 | W29: 10000 | X29: 0
A30: 2019444 | B30: 1565422 | C30: 31024 | D30: PNSU | E30: UNIDAD DE GESTION TERRITORIAL - UGT | F30: 12973 | G30: 1565422 | H30: 1565422 | I30: 0 | J30: 0 | K30: 0 | L30: DESACTIVADO PERMANENTE | M30: OBRA | R30: Concluido - Convenio Cerrado | S30: Concluido | T30: Convenio Cerrado | V30: 1856225 | W30: 0 | X30: 0
A31: 2019446 | B31: 221954 | C31: 29961 | D31: PNSU | E31: UNIDAD DE GESTION TERRITORIAL - UGT | F31: 12837 | G31: 1518234 | H31: 1574440.1 | I31: 1625796.7 | J31: 0 | K31: 0 | L31: ACTIVO | M31: OBRA | N31: 1486755.2 | O31: 1486755.2 | P31: 1486755.2 | Q31: 37168.89 | R31: Concluido - Convenio Cerrado | S31: Concluido | T31: Convenio Cerrado | V31: 1549609.9 | W31: 0 | X31: 0
A32: 2021584 | B32: 1999513 | C32: 31162 | D32: PNSU | E32: UNIDAD DE GESTION TERRITORIAL - UGT | F32: 18122 | G32: 1999513 | H32: 1999513 | I32: 1637768.9 | J32: 0 | K32: 0 | L32: CERRADO | M32: OBRA | R32: Concluido - Liquidada | S32: Concluido | T32: Liquidada | V32: 616052.82 | W32: 0 | X32: 0
A33: 2021877 | B33: 6804821 | C33: 30755 | D33: PNSU | E33: UNIDAD DE GESTION TERRITORIAL - UGT | F33: 702 | G33: 6804821 | H33: 6804821 | I33: 9497902.3 | J33: 0 | K33: 0 | L33: CERRADO | M33: OBRA | N33: 6622142 | O33: 7304641 | P33: 320809.13 | Q33: 288728.22 | R33: Concluido - Convenio Cerrado | S33: Concluido | T33: Convenio Cerrado | V33: 7447670.8 | W33: 0 | X33: 0
A34: 2022711 | B34: 3546394 | C34: 31063 | D34: PNSU | E34: UNIDAD DE GESTION TERRITORIAL - UGT | F34: 6336 | G34: 2899585 | H34: 2899585 | I34: 0 | J34: 0 | K34: 0 | L34: DESACTIVADO PERMANENTE | M34: OBRA | R34: Concluido - Convenio Cerrado | S34: Concluido | T34: Convenio Cerrado | V34: 2847100 | W34: 0 | X34: 0
A35: 2022722 | B35: 18278862 | C35: 48297 | D35: PNSU | E35: UNIDAD DE GESTION TERRITORIAL - UGT | F35: 9311 | G35: 42888139 | H35: 43126732 | I35: 14201456 | J35: 121768.69 | K35: 377880 | L35: ACTIVO | M35: OBRA (Expediente Saldo) | R35: En elaboración - En Proceso | S35: En elaboración | T35: En Proceso
A36: 2022945 | B36: 7429337 | C36: 30760 | D36: PNSU | E36: UNIDAD DE GESTION TERRITORIAL - UGT | F36: 9992 | G36: 9814397.7 | H36: 9814397.7 | I36: 9574525.4 | J36: 0 | K36: 0 | L36: CERRADO | M36: OBRA | N36: 7032213 | O36: 7383824 | P36: 397124 | Q36: 397124 | R36: Concluido - Liquidada | S36: Concluido | T36: Liquidada | V36: 8286721 | W36: 491835.37 | X36: 0
A37: 2025630 | B37: 870922 | C37: 30761 | D37: PNSU | E37: UNIDAD DE GESTION TERRITORIAL - UGT | F37: 19736 | G37: 870922 | H37: 870922 | I37: 2104123.4 | J37: 0 | K37: 0 | L37: CERRADO | M37: OBRA | N37: 1011471.4 | O37: 1222558.7 | R37: Concluido - Convenio Cerrado | S37: Concluido | T37: Convenio Cerrado | V37: 1222558.7 | W37: 0 | X37: 0
A38: 2025660 | B38: 1994896 | C38: 31081 | D38: PNSU | E38: UNIDAD DE GESTION TERRITORIAL - UGT | F38: 21765 | G38: 1994896 | H38: 1994896 | I38: 1375338.1 | J38: 0 | K38: 0 | L38: ACTIVO | M38: OBRA | R38: Concluido - En Liquidación | S38: Concluido | T38: En Liquidación | V38: 1897011.5 | W38: 95000 | X38: 0
A39: 2026355 | B39: 687022 | C39: 30819 | D39: PNSU | E39: UNIDAD DE GESTION TERRITORIAL - UGT | F39: 20292 | G39: 687022 | H39: 687022 | I39: 678412 | J39: 0 | K39: 0 | L39: CERRADO | M39: OBRA | N39: 666412 | O39: 666412 | P39: 0 | Q39: 12000 | R39: Concluido - En Liquidación | S39: Concluido | T39: En Liquidación | V39: 666411.99 | W39: 0 | X39: 0
A40: 2027825 | B40: 1067190 | C40: 30632 | D40: PNSU | E40: UNIDAD DE GESTION TERRITORIAL - UGT | F40: 25559 | G40: 1067190 | H40: 1067190 | I40: 611037.05 | J40: 0 | K40: 0 | L40: ACTIVO | M40: OBRA | N40: 891114.94 | O40: 673952.48 | P40: 20682.2 | Q40: 15642 | R40: Concluido - Liquidada | S40: Concluido | T40: Liquidada | V40: 777642.14 | W40: 0 | X40: 0
A41: 2027902 | B41: 3997661 | C41: 31039 | D41: PNSU | E41: UNIDAD DE GESTION TERRITORIAL - UGT | F41: 27852 | G41: 3997661 | H41: 3997661 | I41: 9818405.8 | J41: 0 | K41: 0 | L41: ACTIVO | M41: OBRA | R41: Concluido - Convenio Cerrado | S41: Concluido | T41: Convenio Cerrado | V41: 9778787.8 | W41: 0 | X41: 0
A42: 2027995 | B42: 1327607 | C42: 31191 | D42: PNSU | E42: UNIDAD DE GESTION TERRITORIAL - UGT | F42: 25133 | G42: 1327607 | H42: 1327607 | I42: 0 | J42: 0 | K42: 0 | L42: DESACTIVADO PERMANENTE | M42: OBRA | R42: Concluido - Convenio Cerrado | S42: Concluido | T42: Convenio Cerrado | V42: 1091548.9 | W42: 0 | X42: 0
A43: 2029429 | B43: 1992916 | C43: 30677 | D43: PNSU | E43: UNIDAD DE GESTION TERRITORIAL - UGT | F43: 14941 | G43: 1992916 | H43: 2459749.5 | I43: 4014698.7 | J43: 0 | K43: 0 | L43: CERRADO | M43: OBRA | N43: 2259738.6 | O43: 2459749.5 | P43: 2259738.6 | Q43: 80916.73 | R43: Concluido - Convenio Cerrado | S43: Concluido | T43: Convenio Cerrado | V43: 2988341.8 | W43: 0 | X43: 0
A44: 2030174 | B44: 733505 | C44: 31229 | D44: PNSU | E44: UNIDAD DE GESTION TERRITORIAL - UGT | F44: 24322 | G44: 733505 | H44: 733505 | I44: 0 | J44: 0 | K44: 0 | L44: DESACTIVADO PERMANENTE | M44: OBRA | R44: Concluido - Por recepcionar | S44: Concluido | T44: Por recepcionar
A45: 2030176 | B45: 4347941 | C45: 30585 | D45: PNSU | E45: UNIDAD DE GESTION TERRITORIAL - UGT | F45: 6222 | G45: 4347941 | H45: 4347941 | I45: 0 | J45: 0 | K45: 0 | L45: CERRADO | M45: OBRA | N45: 4167941 | O45: 4163773 | P45: 166635.7 | Q45: 149972.13 | R45: Concluido - Convenio Cerrado | S45: Concluido | T45: Convenio Cerrado | V45: 4347941 | W45: 0 | X45: 0
A46: 2030267 | B46: 1709257 | C46: 30144 | D46: PNSU | E46: UNIDAD DE GESTION TERRITORIAL - UGT | F46: 30355 | G46: 1709257 | H46: 1709257 | I46: 0 | J46: 0 | K46: 0 | L46: CERRADO | M46: OBRA | N46: 1049114.9 | O46: 944203.41 | R46: Concluido - Convenio Cerrado | S46: Concluido | T46: Convenio Cerrado | V46: 244045.9 | W46: 0 | X46: 0
A47: 2030569 | B47: 1772806 | C47: 30316 | D47: PNSU | E47: UNIDAD DE GESTION TERRITORIAL - UGT | F47: 10913 | G47: 1772806 | H47: 1772806 | I47: 1970766.4 | J47: 0 | K47: 0 | L47: CERRADO | M47: OBRA | N47: 1617767.9 | O47: 1696956.9 | P47: 151020.52 | Q47: 166122.57 | R47: Concluido - Convenio Cerrado | S47: Concluido | T47: Convenio Cerrado | V47: 2014090.8 | W47: 0 | X47: 0
A48: 2030570 | B48: 1619400 | C48: 30317 | D48: PNSU | E48: UNIDAD DE GESTION TERRITORIAL - UGT | F48: 15747 | G48: 1619400 | H48: 1652653.3 | I48: 2821076 | J48: 0 | K48: 0 | L48: CERRADO | M48: OBRA | N48: 1483760.9 | O48: 1335384.8 | P48: 135612.4 | Q48: 122051.26 | R48: Concluido - Por recepcionar | S48: Concluido | T48: Por recepcionar
A49: 2030573 | B49: 1043980 | C49: 31193 | D49: PNSU | E49: UNIDAD DE GESTION TERRITORIAL - UGT | F49: 26698 | G49: 1357419 | H49: 1043980 | I49: 0 | J49: 0 | K49: 0 | L49: DESACTIVADO PERMANENTE | M49: OBRA | R49: Concluido - Convenio Cerrado | S49: Concluido | T49: Convenio Cerrado | V49: 504883.47 | W49: 0 | X49: 0
A50: 2030587 | B50: 106444 | C50: 30686 | D50: PNSU | E50: UNIDAD DE GESTION TERRITORIAL - UGT | F50: 5781 | G50: 106444 | H50: 95931.24 | I50: 131090.24 | J50: 0 | K50: 0 | L50: ACTIVO | M50: OBRA | N50: 106444 | O50: 106444 | R50: Concluido - Convenio Cerrado | S50: Concluido | T50: Convenio Cerrado | V50: 123433.27 | W50: 0 | X50: 0
A51: 2030588 | B51: 1957796 | C51: 30687 | D51: PNSU | E51: UNIDAD DE GESTION TERRITORIAL - UGT | F51: 6845 | G51: 1957796 | H51: 1957796 | I51: 496883.02 | J51: 0 | K51: 0 | L51: ACTIVO | M51: OBRA | N51: 457448 | O51: 511914 | R51: Concluido - Liquidada | S51: Concluido | T51: Liquidada | V51: 457448 | W51: 10000 | X51: 0
A52: 2030606 | B52: 1195259 | C52: 31230 | D52: PNSU | E52: UNIDAD DE GESTION TERRITORIAL - UGT | F52: 30664 | G52: 1195259 | H52: 1195259 | I52: 255587.47 | J52: 0 | K52: 0 | L52: CERRADO | M52: OBRA | R52: Concluido - Convenio Cerrado | S52: Concluido | T52: Convenio Cerrado | V52: 899997.91 | W52: 0 | X52: 0
A53: 2030723 | B53: 1965163 | C53: 29603 | D53: PNSU | E53: UNIDAD DE GESTION TERRITORIAL - UGT | F53: 14747 | G53: 1965163 | H53: 1965163 | I53: 0 | J53: 0 | K53: 0 | L53: DESACTIVADO PERMANENTE | M53: EXPEDIENTE TECNICO | N53: 0 | O53: 54000 | R53: Concluido - Convenio Cerrado | S53: Concluido | T53: Convenio Cerrado
A54: 2030737 | B54: 363672 | C54: 30400 | D54: PNSU | E54: UNIDAD DE GESTION TERRITORIAL - UGT | F54: 34814 | G54: 363672 | H54: 363672 | I54: 0 | J54: 0 | K54: 0 | L54: DESACTIVADO PERMANENTE | M54: OBRA | N54: 355816 | O54: 385815.99 | P54: 355816 | Q54: 24500 | R54: Concluido - Convenio Cerrado | S54: Concluido | T54: Convenio Cerrado | V54: 385815.99 | W54: 0 | X54: 0
A55: 2030738 | B55: 35332632 | C55: 30395 | D55: PNSU | E55: UNIDAD DE GESTION TERRITORIAL - UGT | F55: 28632 | G55: 35332632 | H55: 35332632 | I55: 0 | J55: 0 | K55: 0 | L55: DESACTIVADO PERMANENTE | M55: OBRA | N55: 18400000 | O55: 18400000 | P55: 551860 | Q55: 496674 | R55: Concluido - Convenio Cerrado | S55: Concluido | T55: Convenio Cerrado | V55: 21085872 | W55: 0 | X55: 0
A56: 2030755 | B56: 16291365 | C56: 30740 | D56: PNSU | E56: UNIDAD DE GESTION TERRITORIAL - UGT | F56: 1960 | G56: 19663445 | H56: 19788110 | I56: 22497249 | J56: 0 | K56: 0 | L56: ACTIVO | M56: OBRA | N56: 15316499 | O56: 16057079 | P56: 658711.41 | Q56: 592840.27 | R56: Paralizada - Permanente - Incumplimiento contractual | S56: Paralizada | T56: Permanente | U56: Incumplimiento contractual
A57: 2030756 | B57: 13958899 | C57: 30871 | D57: PNSU | E57: UNIDAD DE GESTION TERRITORIAL - UGT | F57: 29738 | G57: 13658899 | H57: 13658899 | I57: 11732422 | J57: 0 | K57: 0 | L57: CERRADO | M57: OBRA | N57: 7893538.2 | O57: 7734514.5 | P57: 126246.45 | Q57: 113621.81 | R57: Concluido - Convenio Cerrado | S57: Concluido | T57: Convenio Cerrado | V57: 7843630.8 | W57: 771805.5 | X57: 2808801
A58: 2030773 | B58: 33313 | C58: 31316 | D58: PNSU | E58: UNIDAD DE GESTION TERRITORIAL - UGT | F58: 29785 | G58: 33313 | H58: 33313 | I58: 0 | J58: 0 | K58: 0 | L58: DESACTIVADO PERMANENTE | M58: OBRA | R58: Concluido - En Liquidación | S58: Concluido | T58: En Liquidación | V58: 21625.68 | W58: 0 | X58: 0
A59: 2031492 | B59: 785962 | C59: 31287 | D59: PNSU | E59: UNIDAD DE GESTION TERRITORIAL - UGT | F59: 5806 | G59: 785962 | H59: 785962 | I59: 579126.43 | J59: 0 | K59: 0 | L59: CERRADO | M59: OBRA | R59: Concluido - Convenio Cerrado | S59: Concluido | T59: Convenio Cerrado | V59: 545376.43 | W59: 0 | X59: 0
A60: 2031641 | B60: 25648761 | C60: 30953 | D60: PNSU | E60: UNIDAD DE GESTION TERRITORIAL - UGT | F60: 23828 | G60: 24856957 | H60: 24856957 | I60: 25047057 | J60: 0 | K60: 0 | L60: CERRADO | M60: OBRA | N60: 22800000 | O60: 22800000 | P60: 830547.49 | Q60: 697939.07 | R60: Concluido - Convenio Cerrado | S60: Concluido | T60: Convenio Cerrado | V60: 24466291 | W60: 580523.95 | X60: 0
A61: 2031691 | B61: 40513748 | C61: 47179 | D61: PNSU | E61: UNIDAD DE GESTION TERRITORIAL - UGT | F61: 34548 | G61: 40825969 | H61: 39532503 | I61: 29513589 | J61: 9414272.2 | K61: 18956731 | L61: ACTIVO | M61: OBRA | N61: 37327968 | O61: 37327357 | P61: 1862723.8 | Q61: 1420721.6 | R61: En Ejecución - Atrasada - Incremento de Actividades y Plazos al Cronograma | S61: En Ejecución | T61: Atrasada | U61: Incremento de Actividades y Plazos al Cronograma
A62: 2032127 | B62: 59548 | C62: 30751 | D62: PNSU | E62: UNIDAD DE GESTION TERRITORIAL - UGT | F62: 24750 | G62: 59548 | H62: 59548 | I62: 71686.35 | J62: 0 | K62: 0 | L62: CERRADO | M62: OBRA | N62: 58824 | O62: 65744.11 | R62: Concluido - Convenio Cerrado | S62: Concluido | T62: Convenio Cerrado | V62: 66106.35 | W62: 0 | X62: 0
A63: 2036186 | B63: 1522502 | C63: 30758 | D63: PNSU | E63: UNIDAD DE GESTION TERRITORIAL - UGT | F63: 34561 | G63: 1522502 | H63: 1522502 | I63: 1661311.9 | J63: 0 | K63: 0 | L63: CERRADO | M63: OBRA | N63: 1479042 | O63: 1617080 | R63: Concluido - Convenio Cerrado | S63: Concluido | T63: Convenio Cerrado | V63: 1598748.9 | W63: 0 | X63: 0
A64: 2036303 | B64: 235361 | C64: 31115 | D64: PNSU | E64: UNIDAD DE GESTION TERRITORIAL - UGT | F64: 32404 | G64: 235361 | H64: 235361 | I64: 552315.96 | J64: 0 | K64: 0 | L64: ACTIVO | M64: OBRA | R64: Concluido - Convenio Cerrado | S64: Concluido | T64: Convenio Cerrado | V64: 537528.42 | W64: 0 | X64: 0
A65: 2037422 | B65: 521570 | C65: 31011 | D65: PNSU | E65: UNIDAD DE GESTION TERRITORIAL - UGT | F65: 37351 | G65: 728669 | H65: 521570 | I65: 0 | J65: 0 | K65: 0 | L65: DESACTIVADO PERMANENTE | M65: OBRA | R65: Concluido - Convenio Cerrado | S65: Concluido | T65: Convenio Cerrado | V65: 728670.4 | W65: 0 | X65: 0
A66: 2037622 | B66: 23190280 | C66: 30764 | D66: PNSU | E66: UNIDAD DE GESTION TERRITORIAL - UGT | F66: 28929 | G66: 25454632 | H66: 25454632 | I66: 27198578 | J66: 0 | K66: 0 | L66: CERRADO | M66: OBRA | N66: 23039293 | O66: 23039293 | R66: Concluido - En Liquidación | S66: Concluido | T66: En Liquidación | V66: 23039293 | W66: 0 | X66: 0
A67: 2038458 | B67: 15543225 | C67: 48113 | D67: PNSU | E67: UNIDAD DE GESTION TERRITORIAL - UGT | F67: 25707 | G67: 24400614 | H67: 28482573 | I67: 25181980 | J67: 0 | K67: 379516 | L67: ACTIVO | M67: OBRA (Expediente Saldo) | R67: En elaboración - Paralizado | S67: En elaboración | T67: Paralizado
A68: 2038593 | B68: 5912500 | C68: 31171 | D68: PNSU | E68: UNIDAD DE GESTION TERRITORIAL - UGT | F68: 9652 | G68: 5912500 | H68: 5912500 | I68: 89783.69 | J68: 0 | K68: 0 | L68: ACTIVO | M68: OBRA | R68: Concluido - Convenio Cerrado | S68: Concluido | T68: Convenio Cerrado | V68: 5040806.7 | W68: 0 | X68: 0
A69: 2015101 | B69: 89900 | C69: 31082 | D69: PNSU | E69: UNIDAD DE GESTION TERRITORIAL - UGT | F69: 32693 | G69: 89900 | H69: 89900 | I69: 0 | J69: 0 | K69: 0 | L69: DESACTIVADO PERMANENTE | M69: OBRA | R69: Concluido - Convenio Cerrado | S69: Concluido | T69: Convenio Cerrado | V69: 100576.31 | W69: 0 | X69: 0
A70: 2015819 | B70: 0 | C70: 38063 | D70: PNSU | E70: UNIDAD DE PROYECTOS - AREA DE PROYECTOS ESPECIALES | F70: 0 | G70: 0 | M70: OBRA | N70: 0 | O70: 64102318 | R70: Concluido - Liquidada | S70: Concluido | T70: Liquidada | V70: 1.1690214e+08 | W70: 22310476
A71: 2017723 | B71: 5928091 | C71: 38119 | D71: PNSU | E71: UNIDAD DE PROYECTOS - AREA DE EJECUCION DE PROYECTOS | F71: 6507 | G71: 24800478 | H71: 29877369 | I71: 31457663 | J71: 0 | K71: 18651 | L71: ACTIVO | M71: OBRA | N71: 16935614 | O71: 16803574 | P71: 807059.12 | Q71: 798988.52 | R71: Post Ejecución - Concluida | S71: Post Ejecución | T71: Concluida | V71: 662199.74
A72: 2018502 | B72: 1999475 | C72: 30386 | D72: PNSU | E72: UNIDAD DE GESTION TERRITORIAL - UGT | F72: 4507 | G72: 1999475 | H72: 1999475 | I72: 1835638.1 | J72: 0 | K72: 0 | L72: ACTIVO | M72: OBRA | N72: 715918 | O72: 644325.94 | P72: 715918 | Q72: 13300 | R72: Concluido - Liquidada | S72: Concluido | T72: Liquidada | V72: 245449.47 | W72: 5500 | X72: 0
A73: 2021767 | B73: 1180170 | C73: 30642 | D73: PNSU | E73: UNIDAD DE GESTION TERRITORIAL - UGT | F73: 14181 | G73: 1180170 | H73: 1180170 | I73: 926270.66 | J73: 0 | K73: 0 | L73: CERRADO | M73: OBRA | N73: 1062363.3 | O73: 988309.03 | P73: 41822.55 | Q73: 31630.5 | R73: Concluido - Convenio Cerrado | S73: Concluido | T73: Convenio Cerrado | V73: 1039185.1 | W73: 0 | X73: 0
A74: 2021878 | B74: 5194685 | C74: 31239 | D74: PNSU | E74: UNIDAD DE GESTION TERRITORIAL - UGT | F74: 16679 | G74: 8719891 | H74: 8719891 | I74: 8797695.1 | J74: 0 | K74: 0 | L74: CERRADO | M74: OBRA | R74: Concluido - Por recepcionar | S74: Concluido | T74: Por recepcionar | V74: 8797695.1 | W74: 0 | X74: 0
A75: 2021885 | B75: 4445437 | C75: 30650 | D75: PNSU | E75: UNIDAD DE GESTION TERRITORIAL - UGT | F75: 7048 | G75: 9365050.4 | H75: 9365050.4 | I75: 10453097 | J75: 0 | K75: 0 | L75: CERRADO | M75: OBRA | N75: 8836732.2 | O75: 7231321.5 | P75: 426995.8 | Q75: 358820 | R75: Concluido - Convenio Cerrado | S75: Concluido | T75: Convenio Cerrado | V75: 12185911 | W75: 849283.33 | X75: 0
A76: 2022696 | B76: 5941283 | C76: 30870 | D76: PNSU | E76: UNIDAD DE GESTION TERRITORIAL - UGT | F76: 12759 | G76: 5941283 | H76: 5941283 | I76: 1399994.9 | J76: 0 | K76: 0 | L76: ACTIVO | M76: OBRA | N76: 3646237.9 | O76: 3828007.5 | P76: 260284.83 | Q76: 282734.18 | R76: Concluido - Por recepcionar | S76: Concluido | T76: Por recepcionar | V76: 3812085.1 | W76: 0 | X76: 0
A77: 2022746 | B77: 5311113 | C77: 30020 | D77: PNSU | E77: UNIDAD DE GESTION TERRITORIAL - UGT | F77: 20326 | G77: 5311113 | H77: 5311113 | I77: 4611104.5 | J77: 0 | K77: 0 | L77: ACTIVO | M77: OBRA | N77: 4215031.6 | O77: 3793528.5 | P77: 123446.25 | Q77: 123446.25 | R77: Concluido - Convenio Cerrado | S77: Concluido | T77: Convenio Cerrado | V77: 3932249 | W77: 0 | X77: 0
A78: 2025711 | B78: 1410266 | C78: 31238 | D78: PNSU | E78: UNIDAD DE GESTION TERRITORIAL - UGT | F78: 11388 | G78: 1410266 | H78: 1410266 | I78: 1419822.1 | J78: 0 | K78: 0 | L78: CERRADO | M78: OBRA | R78: Concluido - Convenio Cerrado | S78: Concluido | T78: Convenio Cerrado | V78: 1332009.1 | W78: 35950.06 | X78: 0
A79: 2026833 | B79: 3762609 | C79: 30978 | D79: PNSU | E79: UNIDAD DE GESTION TERRITORIAL - UGT | F79: 4665 | G79: 3762609 | H79: 3762609 | I79: 5296709.5 | J79: 0 | K79: 0 | L79: CERRADO | M79: OBRA | R79: Concluido - Convenio Cerrado | S79: Concluido | T79: Convenio Cerrado | V79: 5296709.5 | W79: 0 | X79: 0
A80: 2027994 | B80: 1402771 | C80: 31182 | D80: PNSU | E80: UNIDAD DE GESTION TERRITORIAL - UGT | F80: 25142 | G80: 1402771 | H80: 1402771 | I80: 0 | J80: 0 | K80: 0 | L80: DESACTIVADO PERMANENTE | M80: OBRA | R80: Concluido - Convenio Cerrado | S80: Concluido | T80: Convenio Cerrado | V80: 1572301.3 | W80: 0 | X80: 0
A81: 2028101 | B81: 1824714 | C81: 31008 | D81: PNSU | E81: UNIDAD DE GESTION TERRITORIAL - UGT | F81: 29858 | G81: 1824714 | H81: 1744048.1 | I81: 1744048.1 | J81: 0 | K81: 0 | L81: ACTIVO | M81: OBRA | R81: Concluido - Convenio Cerrado | S81: Concluido | T81: Convenio Cerrado | V81: 1824714 | W81: 18000 | X81: 0
A82: 2028462 | B82: 2907494 | C82: 31032 | D82: PNSU | E82: UNIDAD DE GESTION TERRITORIAL - UGT | F82: 30375 | G82: 5579400.8 | H82: 5579400.8 | I82: 5143230.7 | J82: 0 | K82: 0 | L82: ACTIVO | M82: OBRA | R82: Concluido - Convenio Cerrado | S82: Concluido | T82: Convenio Cerrado | V82: 4485927.7 | W82: 0 | X82: 0
A83: 2029666 | B83: 1048314 | C83: 31309 | D83: PNSU | E83: UNIDAD DE GESTION TERRITORIAL - UGT | F83: 31191 | G83: 1048314 | H83: 1048314 | I83: 0 | J83: 0 | K83: 0 | L83: DESACTIVADO PERMANENTE | M83: OBRA | R83: Concluido - Convenio Cerrado | S83: Concluido | T83: Convenio Cerrado | V83: 788841.68 | W83: 0 | X83: 0
A84: 2030166 | B84: 1908703 | C84: 30174 | D84: PNSU | E84: UNIDAD DE GESTION TERRITORIAL - UGT | F84: 13040 | G84: 1908703 | H84: 1908703 | I84: 2388346.3 | J84: 0 | K84: 0 | L84: CERRADO | M84: OBRA | N84: 2030692.5 | O84: 1929157.9 | P84: 100000 | Q84: 98700 | R84: Concluido - Convenio Cerrado | S84: Concluido | T84: Convenio Cerrado | V84: 2388346.3 | W84: 0 | X84: 0
A85: 2030173 | B85: 1716562 | C85: 30478 | D85: PNSU | E85: UNIDAD DE GESTION TERRITORIAL - UGT | F85: 21802 | G85: 1716562 | H85: 1716562 | I85: 0 | J85: 0 | K85: 0 | L85: DESACTIVADO PERMANENTE | M85: OBRA | N85: 1692762.1 | O85: 1641979.2 | R85: Concluido - Convenio Cerrado | S85: Concluido | T85: Convenio Cerrado | V85: 1669663.5 | W85: 0 | X85: 0
A86: 2030184 | B86: 1408929 | C86: 30908 | D86: PNSU | E86: UNIDAD DE GESTION TERRITORIAL - UGT | F86: 15516 | G86: 1408929 | H86: 1408929 | I86: 1645609.2 | J86: 0 | K86: 0 | L86: ACTIVO | M86: OBRA | N86: 1488137 | O86: 1631509.2 | P86: 20500 | Q86: 20100 | R86: Concluido - Convenio Cerrado | S86: Concluido | T86: Convenio Cerrado | V86: 1680365.3 | W86: 0 | X86: 0
A87: 2030273 | B87: 1453852 | C87: 31097 | D87: PNSU | E87: UNIDAD DE GESTION TERRITORIAL - UGT | F87: 30489 | G87: 1453852 | H87: 1453852 | I87: 0 | J87: 0 | K87: 0 | L87: DESACTIVADO PERMANENTE | M87: OBRA | R87: Concluido - Convenio Cerrado | S87: Concluido | T87: Convenio Cerrado | V87: 883289.87 | W87: 0 | X87: 0
A88: 2030541 | B88: 1997613 | C88: 30860 | D88: PNSU | E88: UNIDAD DE GESTION TERRITORIAL - UGT | F88: 26015 | G88: 2417418 | H88: 1969485.5 | I88: 2127022.7 | J88: 0 | K88: 0 | L88: CERRADO | M88: OBRA | N88: 1922613.1 | O88: 1730242 | P88: 60000 | Q88: 54000 | R88: Concluido - Convenio Cerrado | S88: Concluido | T88: Convenio Cerrado | V88: 1884179.6 | W88: 54000 | X88: 0
A89: 2030552 | B89: 1717976 | C89: 30728 | D89: PNSU | E89: UNIDAD DE GESTION TERRITORIAL - UGT | F89: 24835 | G89: 1717976 | H89: 1717976 | I89: 1457699.1 | J89: 0 | K89: 0 | L89: CERRADO | M89: OBRA | N89: 1647502.1 | O89: 1482751.9 | R89: Concluido - En Liquidación | S89: Concluido | T89: En Liquidación | V89: 1447475 | W89: 0 | X89: 0
A90: 2030559 | B90: 1725124 | C90: 29995 | D90: PNSU | E90: UNIDAD DE GESTION TERRITORIAL - UGT | F90: 29273 | G90: 1725124 | H90: 1725124 | I90: 1564228.2 | J90: 0 | K90: 0 | L90: CERRADO | M90: OBRA | N90: 409635 | O90: 409635 | P90: 409635 | Q90: 0 | R90: Concluido - Convenio Cerrado | S90: Concluido | T90: Convenio Cerrado | V90: 1740470.7 | W90: 0 | X90: 0
A91: 2030274 | B91: 607000 | C91: 30153 | D91: PNSU | E91: UNIDAD DE GESTION TERRITORIAL - UGT | F91: 32698 | G91: 607000 | H91: 607000 | I91: 0 | J91: 0 | K91: 0 | L91: CERRADO | M91: OBRA | N91: 808065 | O91: 727259 | P91: 808065 | Q91: 0 | R91: Concluido - Convenio Cerrado | S91: Concluido | T91: Convenio Cerrado | V91: 739543.76 | W91: 0 | X91: 0
A92: 2030276 | B92: 960934 | C92: 30979 | D92: PNSU | E92: UNIDAD DE GESTION TERRITORIAL - UGT | F92: 8780 | G92: 960934 | H92: 960934 | I92: 1064799.8 | J92: 0 | K92: 0 | L92: CERRADO | M92: OBRA | P92: 24750 | Q92: 24750 | R92: Concluido - Convenio Cerrado | S92: Concluido | T92: Convenio Cerrado | V92: 1062228.5 | W92: 19389.4 | X92: 0
A93: 2030540 | B93: 1984039 | C93: 30858 | D93: PNSU | E93: UNIDAD DE GESTION TERRITORIAL - UGT | F93: 12970 | G93: 3004670 | H93: 3004670 | I93: 3072693.1 | J93: 0 | K93: 0 | L93: CERRADO | M93: OBRA | N93: 1874826 | O93: 1687260.3 | P93: 60000 | Q93: 54000 | R93: Concluido - Convenio Cerrado | S93: Concluido | T93: Convenio Cerrado | V93: 2894266.5 | W93: 0 | X93: 0
A94: 2030542 | B94: 1775697 | C94: 30865 | D94: PNSU | E94: UNIDAD DE GESTION TERRITORIAL - UGT | F94: 27332 | G94: 1815711.8 | H94: 1480234.8 | I94: 1646743.1 | J94: 0 | K94: 0 | L94: CERRADO | M94: OBRA | N94: 1662698 | O94: 1496341.5 | P94: 60000 | Q94: 54000 | R94: Concluido - Convenio Cerrado | S94: Concluido | T94: Convenio Cerrado | V94: 1503597.3 | W94: 58100 | X94: 0
A95: 2030565 | B95: 1364801 | C95: 31043 | D95: PNSU | E95: UNIDAD DE GESTION TERRITORIAL - UGT | F95: 34007 | G95: 1364801 | H95: 1364801 | I95: 769304.93 | J95: 0 | K95: 0 | L95: ACTIVO | M95: OBRA | R95: Concluido - En Liquidación | S95: Concluido | T95: En Liquidación | V95: 743574.71 | W95: 0 | X95: 0
A96: 2030574 | B96: 1615019 | C96: 31018 | D96: PNSU | E96: UNIDAD DE GESTION TERRITORIAL - UGT | F96: 26814 | G96: 1615019 | H96: 1106722.5 | I96: 1106722.5 | J96: 0 | K96: 0 | L96: CERRADO | M96: OBRA | R96: Concluido - Convenio Cerrado | S96: Concluido | T96: Convenio Cerrado | V96: 1615019 | W96: 0 | X96: 0
A97: 2030599 | B97: 701283 | C97: 30692 | D97: PNSU | E97: UNIDAD DE GESTION TERRITORIAL - UGT | F97: 31304 | G97: 701283 | H97: 701283 | I97: 743729.62 | J97: 0 | K97: 0 | L97: ACTIVO | M97: OBRA | N97: 686886.6 | O97: 686886.6 | P97: 686886.6 | Q97: 0 | R97: Concluido - Liquidada | S97: Concluido | T97: Liquidada | V97: 743729.62 | W97: 13500 | X97: 0
A98: 2030608 | B98: 640505 | C98: 30283 | D98: PNSU | E98: UNIDAD DE GESTION TERRITORIAL - UGT | F98: 30873 | G98: 640505 | H98: 640505 | I98: 0 | J98: 0 | K98: 0 | L98: DESACTIVADO PERMANENTE | M98: OBRA | N98: 669055.97 | O98: 602150.38 | P98: 669055.97 | Q98: 0 | R98: Concluido - En Liquidación | S98: Concluido | T98: En Liquidación | V98: 612800.39 | W98: 0 | X98: 0
A99: 2030610 | B99: 1955811 | C99: 31080 | D99: PNSU | E99: UNIDAD DE GESTION TERRITORIAL - UGT | F99: 22997 | G99: 1955811 | H99: 1955811 | I99: 0 | J99: 0 | K99: 0 | L99: DESACTIVADO PERMANENTE | M99: OBRA | R99: Concluido - Convenio Cerrado | S99: Concluido | T99: Convenio Cerrado | V99: 3225839.4 | W99: 0 | X99: 0
A100: 2030708 | B100: 360500 | C100: 30151 | D100: PNSU | E100: UNIDAD DE GESTION TERRITORIAL - UGT | F100: 30326 | G100: 360500 | H100: 360500 | I100: 0 | J100: 0 | K100: 0 | L100: DESACTIVADO PERMANENTE | M100: OBRA | N100: 266834 | O100: 240151 | P100: 266834 | Q100: 0 | R100: Concluido - Convenio Cerrado | S100: Concluido | T100: Convenio Cerrado | V100: 260262.37 | W100: 0 | X100: 0
...
